GoWebBianchengFix1/README.md
GoWebBianchengFix1/__init__.py
GoWebBianchengFix1/__main__.py
GoWebBianchengFix1/file.epub
GoWebBianchengFix1/index.html
GoWebBianchengFix1/css/__init__.py
GoWebBianchengFix1/css/annotations.css
GoWebBianchengFix1/css/main.css
GoWebBianchengFix1/css/normalize.css
GoWebBianchengFix1/css/popup.css
GoWebBianchengFix1/font/__init__.py
GoWebBianchengFix1/font/fontello.eot
GoWebBianchengFix1/font/fontello.svg
GoWebBianchengFix1/font/fontello.ttf
GoWebBianchengFix1/font/fontello.woff
GoWebBianchengFix1/img/__init__.py
GoWebBianchengFix1/img/annotator-glyph-sprite.png
GoWebBianchengFix1/img/annotator-icon-sprite.png
GoWebBianchengFix1/img/apple-touch-icon.png
GoWebBianchengFix1/img/cancelfullscreen.png
GoWebBianchengFix1/img/close.png
GoWebBianchengFix1/img/fullscreen.png
GoWebBianchengFix1/img/loader.gif
GoWebBianchengFix1/img/menu-icon.png
GoWebBianchengFix1/img/save.png
GoWebBianchengFix1/img/saved.png
GoWebBianchengFix1/img/settings-s.png
GoWebBianchengFix1/img/settings.png
GoWebBianchengFix1/img/star.png
GoWebBianchengFix1/js/__init__.py
GoWebBianchengFix1/js/epub.js
GoWebBianchengFix1/js/epub.min.js
GoWebBianchengFix1/js/epub.min.map
GoWebBianchengFix1/js/hooks.min.js
GoWebBianchengFix1/js/hooks.min.map
GoWebBianchengFix1/js/reader.js
GoWebBianchengFix1/js/reader.js.map
GoWebBianchengFix1/js/reader.min.js
GoWebBianchengFix1/js/reader.min.map
GoWebBianchengFix1/js/hooks/__init__.py
GoWebBianchengFix1/js/hooks/extensions/__init__.py
GoWebBianchengFix1/js/hooks/extensions/highlight.js
GoWebBianchengFix1/js/libs/__init__.py
GoWebBianchengFix1/js/libs/jquery.min.js
GoWebBianchengFix1/js/libs/localforage.min.js
GoWebBianchengFix1/js/libs/screenfull.js
GoWebBianchengFix1/js/libs/screenfull.min.js
GoWebBianchengFix1/js/libs/zip.min.js
GoWebBianchengFix1/js/plugins/__init__.py
GoWebBianchengFix1/js/plugins/hypothesis.js
GoWebBianchengFix1/js/plugins/search.js
go_web_biancheng_fix1-2025.3.25.0.dist-info/METADATA
go_web_biancheng_fix1-2025.3.25.0.dist-info/WHEEL
go_web_biancheng_fix1-2025.3.25.0.dist-info/entry_points.txt
go_web_biancheng_fix1-2025.3.25.0.dist-info/top_level.txt
go_web_biancheng_fix1-2025.3.25.0.dist-info/RECORD
